gscdash/__init__.py
gscdash/course_info.py
gscdash/export_events.py
gscdash/pycanvas/canvas_status.py
gscdash/pycanvas/pycanvas.py
gscdash/pyscope/account.py
gscdash/pyscope/assignment.py
gscdash/pyscope/course.py
gscdash/pyscope/gs_status.py
gscdash/pyscope/person.py
gscdash/pyscope/pyscope.py
gscdash/pyscope/question.py
gscdash-0.0.4.dist-info/LICENSE.TXT
gscdash-0.0.4.dist-info/METADATA
gscdash-0.0.4.dist-info/WHEEL
gscdash-0.0.4.dist-info/top_level.txt
gscdash-0.0.4.dist-info/RECORD
