Metadata-Version: 2.1
Name: gscdash
Version: 0.0.4
Summary: Gradescope-Canvas Dashboard support
Home-page: https://github.com/upenn/gradescope-canvas-dashboard
Author: Zack Ives
Author-email: zives@cis.upenn.edu
Classifier: Programming Language :: Python :: 3
Classifier: License :: OSI Approved :: GNU Affero General Public License v3
Classifier: Operating System :: OS Independent
Requires-Python: >=3.9
License-File: LICENSE.TXT
Requires-Dist: requests
Requires-Dist: html5lib
Requires-Dist: beautifulsoup4
Requires-Dist: canvasapi
Requires-Dist: pandas
Requires-Dist: pytz
Requires-Dist: pyyaml
